{
    "_type": "export",
    "__export_format": 4,
    "__export_date": "2021-03-01T01:34:53.232Z",
    "__export_source": "insomnia.desktop.app:v2020.5.2",
    "resources": [
        {
            "_id": "req_37ed2415191f4ec58644f49a2bc23700",
            "parentId": "fld_cb543ea584ac4248968d6a6023229045",
            "modified": 1614562384935,
            "created": 1614539398483,
            "url": "http://localhost:3000/-0.64554",
            "name": "Get Number Name",
            "description": "",
            "method": "GET",
            "body": {},
            "parameters": [],
            "headers": [],
            "authentication": {},
            "metaSortKey": -1614539398483,
            "isPrivate": false,
            "settingStoreCookies": true,
            "settingSendCookies": true,
            "settingDisableRenderRequestBody": false,
            "settingEncodeUrl": true,
            "settingRebuildPath": true,
            "settingFollowRedirects": "global",
            "_type": "request"
        },
        {
            "_id": "fld_cb543ea584ac4248968d6a6023229045",
            "parentId": "wrk_2eb910d5c1a64992b90bf6ec8839d6f4",
            "modified": 1614562357139,
            "created": 1614562357139,
            "name": "Number Name",
            "description": "",
            "environment": {},
            "environmentPropertyOrder": null,
            "metaSortKey": -1614562357139,
            "_type": "request_group"
        },
        {
            "_id": "wrk_2eb910d5c1a64992b90bf6ec8839d6f4",
            "parentId": null,
            "modified": 1614562451970,
            "created": 1614539381337,
            "name": "NumberName",
            "description": "",
            "scope": null,
            "_type": "workspace"
        },
        {
            "_id": "req_2f7917bde3314f62818fc0b9ee472557",
            "parentId": "wrk_2eb910d5c1a64992b90bf6ec8839d6f4",
            "modified": 1614562344528,
            "created": 1614562338381,
            "url": "http://localhost:3000/ping",
            "name": "Ping",
            "description": "",
            "method": "GET",
            "body": {},
            "parameters": [],
            "headers": [],
            "authentication": {},
            "metaSortKey": -1614539398533,
            "isPrivate": false,
            "settingStoreCookies": true,
            "settingSendCookies": true,
            "settingDisableRenderRequestBody": false,
            "settingEncodeUrl": true,
            "settingRebuildPath": true,
            "settingFollowRedirects": "global",
            "_type": "request"
        },
        {
            "_id": "env_290296e5454effee6f438c9431b8f73199f82698",
            "parentId": "wrk_2eb910d5c1a64992b90bf6ec8839d6f4",
            "modified": 1614539381474,
            "created": 1614539381474,
            "name": "Base Environment",
            "data": {},
            "dataPropertyOrder": null,
            "color": null,
            "isPrivate": false,
            "metaSortKey": 1614539381474,
            "_type": "environment"
        },
        {
            "_id": "jar_290296e5454effee6f438c9431b8f73199f82698",
            "parentId": "wrk_2eb910d5c1a64992b90bf6ec8839d6f4",
            "modified": 1614539381477,
            "created": 1614539381477,
            "name": "Default Jar",
            "cookies": [],
            "_type": "cookie_jar"
        },
        {
            "_id": "spc_12ae3ce7abfe44e9aeefa3dc587cd366",
            "parentId": "wrk_2eb910d5c1a64992b90bf6ec8839d6f4",
            "modified": 1614539381344,
            "created": 1614539381344,
            "fileName": "NumberName",
            "contents": "",
            "contentType": "yaml",
            "_type": "api_spec"
        }
    ]
}